{"Culture-related controversies": ["primary", "monolingual fr", 0, 41], "Units of time": ["primary", "monolingual fr", 1, 65], "Information science": ["primary", "monolingual fr", 2, 187], "Clothing": ["primary", "monolingual fr", 3, 171], "Government agencies": ["primary", "monolingual fr", 4, 33], "Mathematical proofs": ["primary", "monolingual en", 5, 63], "Business process": ["primary", "monolingual en", 6, 440], "Scientific buildings": ["primary", "monolingual en", 7, 277], "Social groups": ["primary", "monolingual en", 8, 1643], "Problem behavior": ["primary", "monolingual en", 9, 73], "Symbols": ["primary", "monolingual en", 10, 1085], "Religion stubs": ["primary", "monolingual en", 11, 1593], "Mass media industry": ["primary", "monolingual en", 12, 788], "Oral communication": ["primary", "monolingual en", 13, 427], "Film": ["primary", "monolingual en", 14, 1777], "Mass media stubs": ["primary", "monolingual en", 15, 419], "Language interpretation": ["primary", "monolingual en", 16, 40], "Geographic literature": ["primary", "monolingual en", 17, 136], "Information privacy": ["primary", "monolingual en", 18, 148], "Government audit": ["primary", "monolingual en", 19, 63], "Energy economics": ["primary", "bilingual", 20, 48], "Engineering disciplines": ["primary", "bilingual", 21, 444], "Comparisons": ["primary", "bilingual", 22, 586], "Creativity": ["primary", "bilingual", 23, 76], "Human activities": ["primary", "bilingual", 24, 3530], "Rights": ["primary", "bilingual", 25, 136], "Temporal rates": ["primary", "bilingual", 26, 46], "History of mathematics": ["primary", "bilingual", 27, 144], "Mathematicians": ["primary", "bilingual", 28, 110], "Trade": ["primary", "bilingual", 29, 2394], "Cultural trends": ["primary", "bilingual", 30, 362], "News": ["primary", "bilingual", 31, 74], "Cultural mass media": ["primary", "bilingual", 32, 76]}